{"GlobalPropertiesHash":"wcu0b4Nwz4hAupEFYFbUXIKFFu72iEv37uDzvgNOB8U=","FingerprintPatternsHash":"gq3WsqcKBUGTSNle7RKKyXRIwh7M8ccEqOqYvIzoM04=","PropertyOverridesHash":"8ZRc1sGeVrPBx4lD717BgRaQekyh78QKV9SKsdt638U=","InputHashes":["Ki3mYdRukbowPdzJqULjsUrQAIFvTFOPe6d3yXYjs8c=","SM083k/pSeI2qoVgise3Ge9tEq2HhJ/Im8AuvGenEhU=","V2Vm1lBAwLL6Ym5Z2konJI/dVgP3MzNQHfZ42OhsCxo=","2VevCpKGm3rHjCTKPCT04EhlT1mEmwFo\u002BqP2H7eUnrg=","2kw81pJnzUGRrjpI6zrOujnjzN37MUzcofbwCHoXtVE=","hJSlpY/NqW\u002BjC5a3BgmJgVRUbsLtWRJFpa8JOBV2xko=","vaEOCGuJRnDj2zDh8xtDAXnHv49nmccGAJcuiMQd3eU=","el9FJMfp8dd8EpRWyh5SReR5QF6\u002B8zyDaZft2UInTVw=","x3UuXR718nncL95TgBlfgxz9PIiMb37a9Ebh1dmiD7s=","97iQgb0hopaC7SeVtOLqdbqRlxdrwOUttBqgnbGTx4c=","swotw6XIRViBU\u002B9m5DXguwrPI4jdvSHELq7sNwPe4Ko=","/wQCupMjYq7EaiKclJP3p8n3lqjQq7K8muiiRyheYTo=","8g6T2/\u002BehvmKr4YTU9DWbkPSyFikXntiky1C3amVXjw=","Hnw//eSCmBqJwKZZxce/ojA2dS2FAH6zYmadji9Lk6Y=","kez8XCSrNo5VDKoqG4Co/4gpM8RE9w85CBnGFJ\u002BZ2bI=","IbI\u002BfpE8xYM4hQlZs36b\u002BLm90rh5IWjLMtjt7IHJS6A=","ys\u002BAaohvQMy8C9f\u002BVqIDMnzJnwrVYnpY3aO9hDEh6Qo=","TBWoMUwPBqe7P8r2061Q5KJXitFgBskYS8y4yw1h8KI=","h013ktzRF/fNoQPCC83TgB3U\u002BzDbWo3IZxN95YhYWyQ=","BNlirkRlvVv3fOq5aStN99lcDEXI25quExMwqgYjCtk=","\u002BMAVfvhFQLgpZH4hnZn1W3\u002Bx1dcZK\u002BMZCuEk7y3f92I=","4FGyjqOariPSelVfEsE/qlhpCK0AjCao8s3ZspXZLks=","dunN/cV6lxcAL5hCFacDZmRSVgasFeLbmvE66oEgS\u002BY=","JvVpX/K/vQ48Y268Wz7mZj5PNICaq7C3nbrwbyjluvk=","0NZx\u002BcskxXIbDNEo3T2fPHA/2qPO4bzx3Umfrtcoebk=","U2zX6OQ7w8dvDRmY8JkKcDS4fbulrdn4EV0OZ0G\u002B2KE=","mSfAjxePt9tqlLcv/yzmS\u002BxO81x6tmLPdaYVKkcgkls=","VOBEDgLyD3QZ7AXBHscxphqWO7JLe4aQNZdDwANUB2U="],"CachedAssets":{"IbI\u002BfpE8xYM4hQlZs36b\u002BLm90rh5IWjLMtjt7IHJS6A=":{"Identity":"S:\\Sofija\\Desktop\\projekat swe\\si.26.10.bor\\si.26.10.bor\\Aplikacija\\Majstor_bob\\wwwroot\\pages\\index.html","SourceId":"Majstor_bob","SourceType":"Discovered","ContentRoot":"S:\\Sofija\\Desktop\\projekat swe\\si.26.10.bor\\si.26.10.bor\\Aplikacija\\Majstor_bob\\wwwroot\\","BasePath":"_content/Majstor_bob","RelativePath":"pages/index#[.{fingerprint}]?.html","AssetKind":"All","AssetMode":"All","AssetRole":"Primary","AssetMergeBehavior":null,"AssetMergeSource":"","RelatedAsset":null,"AssetTraitName":null,"AssetTraitValue":null,"Fingerprint":"f9o0ae9201","Integrity":"LTPigGEtnwyxbtv1V76zKsV/NOqHDXc4HSiLy6Rdns8=","CopyToOutputDirectory":"Never","CopyToPublishDirectory":"PreserveNewest","OriginalItemSpec":"wwwroot\\pages\\index.html","FileLength":3050,"LastWriteTime":"2026-06-18T11:16:09.6088852+00:00"},"TBWoMUwPBqe7P8r2061Q5KJXitFgBskYS8y4yw1h8KI=":{"Identity":"S:\\Sofija\\Desktop\\projekat swe\\si.26.10.bor\\si.26.10.bor\\Aplikacija\\Majstor_bob\\wwwroot\\pages\\majstor_profil.html","SourceId":"Majstor_bob","SourceType":"Discovered","ContentRoot":"S:\\Sofija\\Desktop\\projekat swe\\si.26.10.bor\\si.26.10.bor\\Aplikacija\\Majstor_bob\\wwwroot\\","BasePath":"_content/Majstor_bob","RelativePath":"pages/majstor_profil#[.{fingerprint}]?.html","AssetKind":"All","AssetMode":"All","AssetRole":"Primary","AssetMergeBehavior":null,"AssetMergeSource":"","RelatedAsset":null,"AssetTraitName":null,"AssetTraitValue":null,"Fingerprint":"r38pcotf1x","Integrity":"uY47l761t2\u002BDEnxyhtRacJYJ7iH6z62J\u002BZfyKCXRScg=","CopyToOutputDirectory":"Never","CopyToPublishDirectory":"PreserveNewest","OriginalItemSpec":"wwwroot\\pages\\majstor_profil.html","FileLength":5879,"LastWriteTime":"2026-06-27T13:57:07.3614084+00:00"},"x3UuXR718nncL95TgBlfgxz9PIiMb37a9Ebh1dmiD7s=":{"Identity":"S:\\Sofija\\Desktop\\projekat swe\\si.26.10.bor\\si.26.10.bor\\Aplikacija\\Majstor_bob\\wwwroot\\js\\ocene.js","SourceId":"Majstor_bob","SourceType":"Discovered","ContentRoot":"S:\\Sofija\\Desktop\\projekat swe\\si.26.10.bor\\si.26.10.bor\\Aplikacija\\Majstor_bob\\wwwroot\\","BasePath":"_content/Majstor_bob","RelativePath":"js/ocene#[.{fingerprint}]?.js","AssetKind":"All","AssetMode":"All","AssetRole":"Primary","AssetMergeBehavior":null,"AssetMergeSource":"","RelatedAsset":null,"AssetTraitName":null,"AssetTraitValue":null,"Fingerprint":"vqw6kxzvdb","Integrity":"R5MGZmb8rB4ZSOJXrCuwr18O9CXyq07awTqOIuKgaXI=","CopyToOutputDirectory":"Never","CopyToPublishDirectory":"PreserveNewest","OriginalItemSpec":"wwwroot\\js\\ocene.js","FileLength":5966,"LastWriteTime":"2026-06-29T00:16:03.338413+00:00"},"\u002BMAVfvhFQLgpZH4hnZn1W3\u002Bx1dcZK\u002BMZCuEk7y3f92I=":{"Identity":"S:\\Sofija\\Desktop\\projekat swe\\si.26.10.bor\\si.26.10.bor\\Aplikacija\\Majstor_bob\\wwwroot\\pages\\ocene.html","SourceId":"Majstor_bob","SourceType":"Discovered","ContentRoot":"S:\\Sofija\\Desktop\\projekat swe\\si.26.10.bor\\si.26.10.bor\\Aplikacija\\Majstor_bob\\wwwroot\\","BasePath":"_content/Majstor_bob","RelativePath":"pages/ocene#[.{fingerprint}]?.html","AssetKind":"All","AssetMode":"All","AssetRole":"Primary","AssetMergeBehavior":null,"AssetMergeSource":"","RelatedAsset":null,"AssetTraitName":null,"AssetTraitValue":null,"Fingerprint":"ioalu2v9ot","Integrity":"roBrB3I1ZiDWyvpr7W2fj841Uj7VfV5eK1CSAPaBy1U=","CopyToOutputDirectory":"Never","CopyToPublishDirectory":"PreserveNewest","OriginalItemSpec":"wwwroot\\pages\\ocene.html","FileLength":3091,"LastWriteTime":"2026-06-26T16:10:19.0498739+00:00"},"Ki3mYdRukbowPdzJqULjsUrQAIFvTFOPe6d3yXYjs8c=":{"Identity":"S:\\Sofija\\Desktop\\projekat swe\\si.26.10.bor\\si.26.10.bor\\Aplikacija\\Majstor_bob\\wwwroot\\css\\style.css","SourceId":"Majstor_bob","SourceType":"Discovered","ContentRoot":"S:\\Sofija\\Desktop\\projekat swe\\si.26.10.bor\\si.26.10.bor\\Aplikacija\\Majstor_bob\\wwwroot\\","BasePath":"_content/Majstor_bob","RelativePath":"css/style#[.{fingerprint}]?.css","AssetKind":"All","AssetMode":"All","AssetRole":"Primary","AssetMergeBehavior":null,"AssetMergeSource":"","RelatedAsset":null,"AssetTraitName":null,"AssetTraitValue":null,"Fingerprint":"menint1vfr","Integrity":"/iFzzh1AgdA3wSz9/YT7F8GMMzsaSFVLcr5o2HX6Jgw=","CopyToOutputDirectory":"Never","CopyToPublishDirectory":"PreserveNewest","OriginalItemSpec":"wwwroot\\css\\style.css","FileLength":19366,"LastWriteTime":"2026-06-28T13:35:46.166858+00:00"},"4FGyjqOariPSelVfEsE/qlhpCK0AjCao8s3ZspXZLks=":{"Identity":"S:\\Sofija\\Desktop\\projekat swe\\si.26.10.bor\\si.26.10.bor\\Aplikacija\\Majstor_bob\\wwwroot\\pages\\placanje.html","SourceId":"Majstor_bob","SourceType":"Discovered","ContentRoot":"S:\\Sofija\\Desktop\\projekat swe\\si.26.10.bor\\si.26.10.bor\\Aplikacija\\Majstor_bob\\wwwroot\\","BasePath":"_content/Majstor_bob","RelativePath":"pages/placanje#[.{fingerprint}]?.html","AssetKind":"All","AssetMode":"All","AssetRole":"Primary","AssetMergeBehavior":null,"AssetMergeSource":"","RelatedAsset":null,"AssetTraitName":null,"AssetTraitValue":null,"Fingerprint":"ebdxdhm68j","Integrity":"Vk2RMQmwvDuS2i3BZ1nV8B7DmODoQEzxpoSFkGOR8sQ=","CopyToOutputDirectory":"Never","CopyToPublishDirectory":"PreserveNewest","OriginalItemSpec":"wwwroot\\pages\\placanje.html","FileLength":4219,"LastWriteTime":"2026-06-23T13:53:32.6083791+00:00"},"BNlirkRlvVv3fOq5aStN99lcDEXI25quExMwqgYjCtk=":{"Identity":"S:\\Sofija\\Desktop\\projekat swe\\si.26.10.bor\\si.26.10.bor\\Aplikacija\\Majstor_bob\\wwwroot\\pages\\moji_termini.html","SourceId":"Majstor_bob","SourceType":"Discovered","ContentRoot":"S:\\Sofija\\Desktop\\projekat swe\\si.26.10.bor\\si.26.10.bor\\Aplikacija\\Majstor_bob\\wwwroot\\","BasePath":"_content/Majstor_bob","RelativePath":"pages/moji_termini#[.{fingerprint}]?.html","AssetKind":"All","AssetMode":"All","AssetRole":"Primary","AssetMergeBehavior":null,"AssetMergeSource":"","RelatedAsset":null,"AssetTraitName":null,"AssetTraitValue":null,"Fingerprint":"uzsfwfz0ae","Integrity":"dtMP9aEy1xDj94yJvqP0VEqbPo4HWNaHi4WL\u002BbOynME=","CopyToOutputDirectory":"Never","CopyToPublishDirectory":"PreserveNewest","OriginalItemSpec":"wwwroot\\pages\\moji_termini.html","FileLength":7085,"LastWriteTime":"2026-06-29T06:15:32.7939766+00:00"},"97iQgb0hopaC7SeVtOLqdbqRlxdrwOUttBqgnbGTx4c=":{"Identity":"S:\\Sofija\\Desktop\\projekat swe\\si.26.10.bor\\si.26.10.bor\\Aplikacija\\Majstor_bob\\wwwroot\\js\\placanje.js","SourceId":"Majstor_bob","SourceType":"Discovered","ContentRoot":"S:\\Sofija\\Desktop\\projekat swe\\si.26.10.bor\\si.26.10.bor\\Aplikacija\\Majstor_bob\\wwwroot\\","BasePath":"_content/Majstor_bob","RelativePath":"js/placanje#[.{fingerprint}]?.js","AssetKind":"All","AssetMode":"All","AssetRole":"Primary","AssetMergeBehavior":null,"AssetMergeSource":"","RelatedAsset":null,"AssetTraitName":null,"AssetTraitValue":null,"Fingerprint":"ni60f059x6","Integrity":"/x/lpGeSSWAJ4RXGq7LtT\u002B\u002BWoCaxMvy16TDjSfEnC0s=","CopyToOutputDirectory":"Never","CopyToPublishDirectory":"PreserveNewest","OriginalItemSpec":"wwwroot\\js\\placanje.js","FileLength":7421,"LastWriteTime":"2026-06-23T13:53:33.752786+00:00"},"JvVpX/K/vQ48Y268Wz7mZj5PNICaq7C3nbrwbyjluvk=":{"Identity":"S:\\Sofija\\Desktop\\projekat swe\\si.26.10.bor\\si.26.10.bor\\Aplikacija\\Majstor_bob\\wwwroot\\pages\\profil.html","SourceId":"Majstor_bob","SourceType":"Discovered","ContentRoot":"S:\\Sofija\\Desktop\\projekat swe\\si.26.10.bor\\si.26.10.bor\\Aplikacija\\Majstor_bob\\wwwroot\\","BasePath":"_content/Majstor_bob","RelativePath":"pages/profil#[.{fingerprint}]?.html","AssetKind":"All","AssetMode":"All","AssetRole":"Primary","AssetMergeBehavior":null,"AssetMergeSource":"","RelatedAsset":null,"AssetTraitName":null,"AssetTraitValue":null,"Fingerprint":"ncv8y3crty","Integrity":"SeHHhGhUatTWT6rknmYXWBFwJKR\u002B3lMTj3f1SLFyuEs=","CopyToOutputDirectory":"Never","CopyToPublishDirectory":"PreserveNewest","OriginalItemSpec":"wwwroot\\pages\\profil.html","FileLength":13444,"LastWriteTime":"2026-06-29T05:01:06.2088624+00:00"},"SM083k/pSeI2qoVgise3Ge9tEq2HhJ/Im8AuvGenEhU=":{"Identity":"S:\\Sofija\\Desktop\\projekat swe\\si.26.10.bor\\si.26.10.bor\\Aplikacija\\Majstor_bob\\wwwroot\\js\\admin.js","SourceId":"Majstor_bob","SourceType":"Discovered","ContentRoot":"S:\\Sofija\\Desktop\\projekat swe\\si.26.10.bor\\si.26.10.bor\\Aplikacija\\Majstor_bob\\wwwroot\\","BasePath":"_content/Majstor_bob","RelativePath":"js/admin#[.{fingerprint}]?.js","AssetKind":"All","AssetMode":"All","AssetRole":"Primary","AssetMergeBehavior":null,"AssetMergeSource":"","RelatedAsset":null,"AssetTraitName":null,"AssetTraitValue":null,"Fingerprint":"jqsj8854va","Integrity":"xW\u002BEMGho7wuYaRT7vzWg5O\u002BJIPK9PGxuL/Wt4zahVnM=","CopyToOutputDirectory":"Never","CopyToPublishDirectory":"PreserveNewest","OriginalItemSpec":"wwwroot\\js\\admin.js","FileLength":22661,"LastWriteTime":"2026-06-29T06:39:22.8070202+00:00"},"U2zX6OQ7w8dvDRmY8JkKcDS4fbulrdn4EV0OZ0G\u002B2KE=":{"Identity":"S:\\Sofija\\Desktop\\projekat swe\\si.26.10.bor\\si.26.10.bor\\Aplikacija\\Majstor_bob\\wwwroot\\pages\\zakazivanje.html","SourceId":"Majstor_bob","SourceType":"Discovered","ContentRoot":"S:\\Sofija\\Desktop\\projekat swe\\si.26.10.bor\\si.26.10.bor\\Aplikacija\\Majstor_bob\\wwwroot\\","BasePath":"_content/Majstor_bob","RelativePath":"pages/zakazivanje#[.{fingerprint}]?.html","AssetKind":"All","AssetMode":"All","AssetRole":"Primary","AssetMergeBehavior":null,"AssetMergeSource":"","RelatedAsset":null,"AssetTraitName":null,"AssetTraitValue":null,"Fingerprint":"wznggoas0g","Integrity":"fO0KpwAiMpEPtVuU3WBdn2YKXwqSu2ZvEOyIhsEavAo=","CopyToOutputDirectory":"Never","CopyToPublishDirectory":"PreserveNewest","OriginalItemSpec":"wwwroot\\pages\\zakazivanje.html","FileLength":3004,"LastWriteTime":"2026-06-21T13:12:20.4809325+00:00"},"Hnw//eSCmBqJwKZZxce/ojA2dS2FAH6zYmadji9Lk6Y=":{"Identity":"S:\\Sofija\\Desktop\\projekat swe\\si.26.10.bor\\si.26.10.bor\\Aplikacija\\Majstor_bob\\wwwroot\\pages\\admin.html","SourceId":"Majstor_bob","SourceType":"Discovered","ContentRoot":"S:\\Sofija\\Desktop\\projekat swe\\si.26.10.bor\\si.26.10.bor\\Aplikacija\\Majstor_bob\\wwwroot\\","BasePath":"_content/Majstor_bob","RelativePath":"pages/admin#[.{fingerprint}]?.html","AssetKind":"All","AssetMode":"All","AssetRole":"Primary","AssetMergeBehavior":null,"AssetMergeSource":"","RelatedAsset":null,"AssetTraitName":null,"AssetTraitValue":null,"Fingerprint":"9qv8icgjk2","Integrity":"X\u002BuQFzf8OqmbHs1g0ZW053L0WSYFDjpk4yKcJ0NzAzU=","CopyToOutputDirectory":"Never","CopyToPublishDirectory":"PreserveNewest","OriginalItemSpec":"wwwroot\\pages\\admin.html","FileLength":12503,"LastWriteTime":"2026-06-29T06:29:28.3741445+00:00"},"2kw81pJnzUGRrjpI6zrOujnjzN37MUzcofbwCHoXtVE=":{"Identity":"S:\\Sofija\\Desktop\\projekat swe\\si.26.10.bor\\si.26.10.bor\\Aplikacija\\Majstor_bob\\wwwroot\\js\\main.js","SourceId":"Majstor_bob","SourceType":"Discovered","ContentRoot":"S:\\Sofija\\Desktop\\projekat swe\\si.26.10.bor\\si.26.10.bor\\Aplikacija\\Majstor_bob\\wwwroot\\","BasePath":"_content/Majstor_bob","RelativePath":"js/main#[.{fingerprint}]?.js","AssetKind":"All","AssetMode":"All","AssetRole":"Primary","AssetMergeBehavior":null,"AssetMergeSource":"","RelatedAsset":null,"AssetTraitName":null,"AssetTraitValue":null,"Fingerprint":"063o87hu80","Integrity":"\u002BMVDbdRM4f20Pu4hAVv2c0Rtd2CVSTIJNyCGpbKDSkA=","CopyToOutputDirectory":"Never","CopyToPublishDirectory":"PreserveNewest","OriginalItemSpec":"wwwroot\\js\\main.js","FileLength":6067,"LastWriteTime":"2026-06-28T17:57:58.9178258+00:00"},"0NZx\u002BcskxXIbDNEo3T2fPHA/2qPO4bzx3Umfrtcoebk=":{"Identity":"S:\\Sofija\\Desktop\\projekat swe\\si.26.10.bor\\si.26.10.bor\\Aplikacija\\Majstor_bob\\wwwroot\\pages\\register.html","SourceId":"Majstor_bob","SourceType":"Discovered","ContentRoot":"S:\\Sofija\\Desktop\\projekat swe\\si.26.10.bor\\si.26.10.bor\\Aplikacija\\Majstor_bob\\wwwroot\\","BasePath":"_content/Majstor_bob","RelativePath":"pages/register#[.{fingerprint}]?.html","AssetKind":"All","AssetMode":"All","AssetRole":"Primary","AssetMergeBehavior":null,"AssetMergeSource":"","RelatedAsset":null,"AssetTraitName":null,"AssetTraitValue":null,"Fingerprint":"r0bs4mkm5e","Integrity":"y4JYpM8zfbtvUCnvWzgjtfpqeXr5M08nRolTz9MKfmI=","CopyToOutputDirectory":"Never","CopyToPublishDirectory":"PreserveNewest","OriginalItemSpec":"wwwroot\\pages\\register.html","FileLength":22918,"LastWriteTime":"2026-06-21T17:20:12.6545907+00:00"},"2VevCpKGm3rHjCTKPCT04EhlT1mEmwFo\u002BqP2H7eUnrg=":{"Identity":"S:\\Sofija\\Desktop\\projekat swe\\si.26.10.bor\\si.26.10.bor\\Aplikacija\\Majstor_bob\\wwwroot\\js\\chat.js","SourceId":"Majstor_bob","SourceType":"Discovered","ContentRoot":"S:\\Sofija\\Desktop\\projekat swe\\si.26.10.bor\\si.26.10.bor\\Aplikacija\\Majstor_bob\\wwwroot\\","BasePath":"_content/Majstor_bob","RelativePath":"js/chat#[.{fingerprint}]?.js","AssetKind":"All","AssetMode":"All","AssetRole":"Primary","AssetMergeBehavior":null,"AssetMergeSource":"","RelatedAsset":null,"AssetTraitName":null,"AssetTraitValue":null,"Fingerprint":"l5zca85vie","Integrity":"B0lyYb2cwkCsmc7/hIdAYO2oHhqWRmCVs5fAM1bIcp0=","CopyToOutputDirectory":"Never","CopyToPublishDirectory":"PreserveNewest","OriginalItemSpec":"wwwroot\\js\\chat.js","FileLength":8359,"LastWriteTime":"2026-06-29T06:06:40.94667+00:00"},"vaEOCGuJRnDj2zDh8xtDAXnHv49nmccGAJcuiMQd3eU=":{"Identity":"S:\\Sofija\\Desktop\\projekat swe\\si.26.10.bor\\si.26.10.bor\\Aplikacija\\Majstor_bob\\wwwroot\\js\\moje_rezervacije.js","SourceId":"Majstor_bob","SourceType":"Discovered","ContentRoot":"S:\\Sofija\\Desktop\\projekat swe\\si.26.10.bor\\si.26.10.bor\\Aplikacija\\Majstor_bob\\wwwroot\\","BasePath":"_content/Majstor_bob","RelativePath":"js/moje_rezervacije#[.{fingerprint}]?.js","AssetKind":"All","AssetMode":"All","AssetRole":"Primary","AssetMergeBehavior":null,"AssetMergeSource":"","RelatedAsset":null,"AssetTraitName":null,"AssetTraitValue":null,"Fingerprint":"xof88q1yvp","Integrity":"j77BBGaVKTCFbeHpFTmnwaxAxBefspYU3o622A74Enc=","CopyToOutputDirectory":"Never","CopyToPublishDirectory":"PreserveNewest","OriginalItemSpec":"wwwroot\\js\\moje_rezervacije.js","FileLength":9960,"LastWriteTime":"2026-06-29T06:14:47.919399+00:00"},"ys\u002BAaohvQMy8C9f\u002BVqIDMnzJnwrVYnpY3aO9hDEh6Qo=":{"Identity":"S:\\Sofija\\Desktop\\projekat swe\\si.26.10.bor\\si.26.10.bor\\Aplikacija\\Majstor_bob\\wwwroot\\pages\\login.html","SourceId":"Majstor_bob","SourceType":"Discovered","ContentRoot":"S:\\Sofija\\Desktop\\projekat swe\\si.26.10.bor\\si.26.10.bor\\Aplikacija\\Majstor_bob\\wwwroot\\","BasePath":"_content/Majstor_bob","RelativePath":"pages/login#[.{fingerprint}]?.html","AssetKind":"All","AssetMode":"All","AssetRole":"Primary","AssetMergeBehavior":null,"AssetMergeSource":"","RelatedAsset":null,"AssetTraitName":null,"AssetTraitValue":null,"Fingerprint":"r4ic8mmj54","Integrity":"yyY/PNNKRjdUlGLO25ExQEp1N0ZLps5WSGrEWKEWgQs=","CopyToOutputDirectory":"Never","CopyToPublishDirectory":"PreserveNewest","OriginalItemSpec":"wwwroot\\pages\\login.html","FileLength":7028,"LastWriteTime":"2026-06-15T20:08:49.2705871+00:00"},"el9FJMfp8dd8EpRWyh5SReR5QF6\u002B8zyDaZft2UInTVw=":{"Identity":"S:\\Sofija\\Desktop\\projekat swe\\si.26.10.bor\\si.26.10.bor\\Aplikacija\\Majstor_bob\\wwwroot\\js\\moji_termini.js","SourceId":"Majstor_bob","SourceType":"Discovered","ContentRoot":"S:\\Sofija\\Desktop\\projekat swe\\si.26.10.bor\\si.26.10.bor\\Aplikacija\\Majstor_bob\\wwwroot\\","BasePath":"_content/Majstor_bob","RelativePath":"js/moji_termini#[.{fingerprint}]?.js","AssetKind":"All","AssetMode":"All","AssetRole":"Primary","AssetMergeBehavior":null,"AssetMergeSource":"","RelatedAsset":null,"AssetTraitName":null,"AssetTraitValue":null,"Fingerprint":"5pr4m6g34x","Integrity":"OdMKGYPW0mN6OE6armD1ktZhaeHsPW2BSq6qcllY2vc=","CopyToOutputDirectory":"Never","CopyToPublishDirectory":"PreserveNewest","OriginalItemSpec":"wwwroot\\js\\moji_termini.js","FileLength":15887,"LastWriteTime":"2026-06-27T15:02:54.1489353+00:00"},"/wQCupMjYq7EaiKclJP3p8n3lqjQq7K8muiiRyheYTo=":{"Identity":"S:\\Sofija\\Desktop\\projekat swe\\si.26.10.bor\\si.26.10.bor\\Aplikacija\\Majstor_bob\\wwwroot\\js\\profil.js","SourceId":"Majstor_bob","SourceType":"Discovered","ContentRoot":"S:\\Sofija\\Desktop\\projekat swe\\si.26.10.bor\\si.26.10.bor\\Aplikacija\\Majstor_bob\\wwwroot\\","BasePath":"_content/Majstor_bob","RelativePath":"js/profil#[.{fingerprint}]?.js","AssetKind":"All","AssetMode":"All","AssetRole":"Primary","AssetMergeBehavior":null,"AssetMergeSource":"","RelatedAsset":null,"AssetTraitName":null,"AssetTraitValue":null,"Fingerprint":"nwrbjeaax1","Integrity":"\u002BZJxfXxCKjSH1T/GJxo0AUqH5EsVZcJpMDU/EpxQLos=","CopyToOutputDirectory":"Never","CopyToPublishDirectory":"PreserveNewest","OriginalItemSpec":"wwwroot\\js\\profil.js","FileLength":43170,"LastWriteTime":"2026-06-29T05:45:35.1412247+00:00"},"h013ktzRF/fNoQPCC83TgB3U\u002BzDbWo3IZxN95YhYWyQ=":{"Identity":"S:\\Sofija\\Desktop\\projekat swe\\si.26.10.bor\\si.26.10.bor\\Aplikacija\\Majstor_bob\\wwwroot\\pages\\moje_rezervacije.html","SourceId":"Majstor_bob","SourceType":"Discovered","ContentRoot":"S:\\Sofija\\Desktop\\projekat swe\\si.26.10.bor\\si.26.10.bor\\Aplikacija\\Majstor_bob\\wwwroot\\","BasePath":"_content/Majstor_bob","RelativePath":"pages/moje_rezervacije#[.{fingerprint}]?.html","AssetKind":"All","AssetMode":"All","AssetRole":"Primary","AssetMergeBehavior":null,"AssetMergeSource":"","RelatedAsset":null,"AssetTraitName":null,"AssetTraitValue":null,"Fingerprint":"ax5ydx6iwa","Integrity":"foNnOCtiHyx9SZ3nnbMgSwRzRxBH3\u002BPjI7aaUaMfzTY=","CopyToOutputDirectory":"Never","CopyToPublishDirectory":"PreserveNewest","OriginalItemSpec":"wwwroot\\pages\\moje_rezervacije.html","FileLength":3493,"LastWriteTime":"2026-06-24T16:04:31.8392391+00:00"},"swotw6XIRViBU\u002B9m5DXguwrPI4jdvSHELq7sNwPe4Ko=":{"Identity":"S:\\Sofija\\Desktop\\projekat swe\\si.26.10.bor\\si.26.10.bor\\Aplikacija\\Majstor_bob\\wwwroot\\js\\pretraga.js","SourceId":"Majstor_bob","SourceType":"Discovered","ContentRoot":"S:\\Sofija\\Desktop\\projekat swe\\si.26.10.bor\\si.26.10.bor\\Aplikacija\\Majstor_bob\\wwwroot\\","BasePath":"_content/Majstor_bob","RelativePath":"js/pretraga#[.{fingerprint}]?.js","AssetKind":"All","AssetMode":"All","AssetRole":"Primary","AssetMergeBehavior":null,"AssetMergeSource":"","RelatedAsset":null,"AssetTraitName":null,"AssetTraitValue":null,"Fingerprint":"efflxyskfs","Integrity":"pnVXs7lneYqX0VweKc3QkA4ymvRILXIfQXdP5zjIN5s=","CopyToOutputDirectory":"Never","CopyToPublishDirectory":"PreserveNewest","OriginalItemSpec":"wwwroot\\js\\pretraga.js","FileLength":7789,"LastWriteTime":"2026-06-28T23:52:36.6764066+00:00"},"hJSlpY/NqW\u002BjC5a3BgmJgVRUbsLtWRJFpa8JOBV2xko=":{"Identity":"S:\\Sofija\\Desktop\\projekat swe\\si.26.10.bor\\si.26.10.bor\\Aplikacija\\Majstor_bob\\wwwroot\\js\\majstor_profil.js","SourceId":"Majstor_bob","SourceType":"Discovered","ContentRoot":"S:\\Sofija\\Desktop\\projekat swe\\si.26.10.bor\\si.26.10.bor\\Aplikacija\\Majstor_bob\\wwwroot\\","BasePath":"_content/Majstor_bob","RelativePath":"js/majstor_profil#[.{fingerprint}]?.js","AssetKind":"All","AssetMode":"All","AssetRole":"Primary","AssetMergeBehavior":null,"AssetMergeSource":"","RelatedAsset":null,"AssetTraitName":null,"AssetTraitValue":null,"Fingerprint":"5k6ifsnpc6","Integrity":"S//lvbe6S3a0swaNslt30P8qxki69v1W3ALLTyZmk5s=","CopyToOutputDirectory":"Never","CopyToPublishDirectory":"PreserveNewest","OriginalItemSpec":"wwwroot\\js\\majstor_profil.js","FileLength":16351,"LastWriteTime":"2026-06-29T00:10:40.152459+00:00"},"kez8XCSrNo5VDKoqG4Co/4gpM8RE9w85CBnGFJ\u002BZ2bI=":{"Identity":"S:\\Sofija\\Desktop\\projekat swe\\si.26.10.bor\\si.26.10.bor\\Aplikacija\\Majstor_bob\\wwwroot\\pages\\chat.html","SourceId":"Majstor_bob","SourceType":"Discovered","ContentRoot":"S:\\Sofija\\Desktop\\projekat swe\\si.26.10.bor\\si.26.10.bor\\Aplikacija\\Majstor_bob\\wwwroot\\","BasePath":"_content/Majstor_bob","RelativePath":"pages/chat#[.{fingerprint}]?.html","AssetKind":"All","AssetMode":"All","AssetRole":"Primary","AssetMergeBehavior":null,"AssetMergeSource":"","RelatedAsset":null,"AssetTraitName":null,"AssetTraitValue":null,"Fingerprint":"cp4uwm6y7m","Integrity":"sHS\u002BNSBgzPqBwzFC2AEdxLyUQ9PzpYAHT2ktF06bNn8=","CopyToOutputDirectory":"Never","CopyToPublishDirectory":"PreserveNewest","OriginalItemSpec":"wwwroot\\pages\\chat.html","FileLength":2522,"LastWriteTime":"2026-06-20T12:42:58.3233585+00:00"},"V2Vm1lBAwLL6Ym5Z2konJI/dVgP3MzNQHfZ42OhsCxo=":{"Identity":"S:\\Sofija\\Desktop\\projekat swe\\si.26.10.bor\\si.26.10.bor\\Aplikacija\\Majstor_bob\\wwwroot\\js\\api.js","SourceId":"Majstor_bob","SourceType":"Discovered","ContentRoot":"S:\\Sofija\\Desktop\\projekat swe\\si.26.10.bor\\si.26.10.bor\\Aplikacija\\Majstor_bob\\wwwroot\\","BasePath":"_content/Majstor_bob","RelativePath":"js/api#[.{fingerprint}]?.js","AssetKind":"All","AssetMode":"All","AssetRole":"Primary","AssetMergeBehavior":null,"AssetMergeSource":"","RelatedAsset":null,"AssetTraitName":null,"AssetTraitValue":null,"Fingerprint":"9tevqex4p7","Integrity":"Q0HLbhE7u8eihQNVTVlKwo3O7bFgNWKVI4penRprHgQ=","CopyToOutputDirectory":"Never","CopyToPublishDirectory":"PreserveNewest","OriginalItemSpec":"wwwroot\\js\\api.js","FileLength":29634,"LastWriteTime":"2026-06-29T06:38:49.6180224+00:00"},"8g6T2/\u002BehvmKr4YTU9DWbkPSyFikXntiky1C3amVXjw=":{"Identity":"S:\\Sofija\\Desktop\\projekat swe\\si.26.10.bor\\si.26.10.bor\\Aplikacija\\Majstor_bob\\wwwroot\\js\\zakazivanje.js","SourceId":"Majstor_bob","SourceType":"Discovered","ContentRoot":"S:\\Sofija\\Desktop\\projekat swe\\si.26.10.bor\\si.26.10.bor\\Aplikacija\\Majstor_bob\\wwwroot\\","BasePath":"_content/Majstor_bob","RelativePath":"js/zakazivanje#[.{fingerprint}]?.js","AssetKind":"All","AssetMode":"All","AssetRole":"Primary","AssetMergeBehavior":null,"AssetMergeSource":"","RelatedAsset":null,"AssetTraitName":null,"AssetTraitValue":null,"Fingerprint":"asly4wdzy0","Integrity":"NsnDXG16o8XZ\u002B7pIINgfuNZH\u002BiEkbQ95LkhBlN2inIs=","CopyToOutputDirectory":"Never","CopyToPublishDirectory":"PreserveNewest","OriginalItemSpec":"wwwroot\\js\\zakazivanje.js","FileLength":4955,"LastWriteTime":"2026-06-29T00:18:03.3720454+00:00"},"dunN/cV6lxcAL5hCFacDZmRSVgasFeLbmvE66oEgS\u002BY=":{"Identity":"S:\\Sofija\\Desktop\\projekat swe\\si.26.10.bor\\si.26.10.bor\\Aplikacija\\Majstor_bob\\wwwroot\\pages\\pretraga.html","SourceId":"Majstor_bob","SourceType":"Discovered","ContentRoot":"S:\\Sofija\\Desktop\\projekat swe\\si.26.10.bor\\si.26.10.bor\\Aplikacija\\Majstor_bob\\wwwroot\\","BasePath":"_content/Majstor_bob","RelativePath":"pages/pretraga#[.{fingerprint}]?.html","AssetKind":"All","AssetMode":"All","AssetRole":"Primary","AssetMergeBehavior":null,"AssetMergeSource":"","RelatedAsset":null,"AssetTraitName":null,"AssetTraitValue":null,"Fingerprint":"fnp1qotura","Integrity":"G0L\u002Bz8lPoOgWQYSWTCIC1aY24peqwvrDNfGBId4nTvU=","CopyToOutputDirectory":"Never","CopyToPublishDirectory":"PreserveNewest","OriginalItemSpec":"wwwroot\\pages\\pretraga.html","FileLength":3863,"LastWriteTime":"2026-06-21T17:01:36.7795012+00:00"}},"CachedCopyCandidates":{}}